pippurge/__init__.py
pippurge/__main__.py
pippurge/cli.py
pip_purge_dep-0.6.0.dist-info/METADATA
pip_purge_dep-0.6.0.dist-info/WHEEL
pip_purge_dep-0.6.0.dist-info/entry_points.txt
pip_purge_dep-0.6.0.dist-info/top_level.txt
pip_purge_dep-0.6.0.dist-info/RECORD
